tiresias/__init__.py
tiresias/__main__.py
tiresias/preprocessor.py
tiresias/tiresias.py
tiresias-0.0.2.dist-info/LICENSE
tiresias-0.0.2.dist-info/METADATA
tiresias-0.0.2.dist-info/WHEEL
tiresias-0.0.2.dist-info/top_level.txt
tiresias-0.0.2.dist-info/RECORD
