Metadata-Version: 2.1
Name: tiresias
Version: 0.0.2
Summary: Pytorch implementation of Tiresias: Predicting Security Events Through Deep Learning
Home-page: https://github.com/Thijsvanede/Tiresias
Author: Thijs van Ede
Author-email: t.s.vanede@utwente.nl
License: UNKNOWN
Platform: UNKNOWN
Classifier: Programming Language :: Python :: 3
Classifier: License :: OSI Approved :: MIT License
Classifier: Operating System :: OS Independent
